flutterwave_api/__init__.py
flutterwave_api/_http/__init__.py
flutterwave_api/_http/http.py
flutterwave_api/configuration/__init__.py
flutterwave_api/configuration/configuration.py
flutterwave_api/exceptions/__init__.py
flutterwave_api/exceptions/authentication_error.py
flutterwave_api/exceptions/authorization_error.py
flutterwave_api/exceptions/bank_error.py
flutterwave_api/exceptions/card_error.py
flutterwave_api/exceptions/configuration_error.py
flutterwave_api/exceptions/flutterwave_error.py
flutterwave_api/exceptions/gateway_error.py
flutterwave_api/exceptions/gateway_timeout_error.py
flutterwave_api/exceptions/invalid_challenge_error.py
flutterwave_api/exceptions/invalid_parameter.py
flutterwave_api/exceptions/invalid_signature_error.py
flutterwave_api/exceptions/not_found_error.py
flutterwave_api/exceptions/request_timeout_error.py
flutterwave_api/exceptions/server_error.py
flutterwave_api/exceptions/service_unavailable_error.py
flutterwave_api/exceptions/test_operation_performed_in_production_error.py
flutterwave_api/exceptions/too_many_requests_error.py
flutterwave_api/exceptions/unexpected_error.py
flutterwave_api/exceptions/upgrade_required_error.py
flutterwave_api/exceptions/http/__init__.py
flutterwave_api/exceptions/http/connection_error.py
flutterwave_api/exceptions/http/invalid_response_error.py
flutterwave_api/exceptions/http/timeout_error.py
flutterwave_api/gateways/__init__.py
flutterwave_api/gateways/base/__init__.py
flutterwave_api/gateways/base/base.py
flutterwave_api/gateways/bills/__init__.py
flutterwave_api/gateways/bills/airtime.py
flutterwave_api/gateways/bills/cable.py
flutterwave_api/gateways/charges/__init__.py
flutterwave_api/gateways/charges/account.py
flutterwave_api/gateways/charges/card.py
flutterwave_api/gateways/charges/mpesa.py
flutterwave_api/gateways/charges/ussd.py
flutterwave_api/gateways/plans/__init__.py
flutterwave_api/gateways/plans/subscriptions/__init__.py
flutterwave_api/gateways/transfers/__init__.py
wave_pay-0.0.12.dist-info/LICENSE
wave_pay-0.0.12.dist-info/METADATA
wave_pay-0.0.12.dist-info/WHEEL
wave_pay-0.0.12.dist-info/top_level.txt
wave_pay-0.0.12.dist-info/RECORD
