Metadata-Version: 2.1
Name: wave-pay
Version: 0.0.12
Summary: Wave-Pay is a Python package that seamlessly allow merchants accept payments on their Python based web apps
Home-page: https://github.com/Lakanbi37/Wave-Pay
Author: Lekan Akanbi
Author-email: lakanbi37@gmail.com
License: UNKNOWN
Project-URL: Bug Tracker, https://github.com/Lakanbi37/Wave-Pay/issues
Platform: UNKNOWN
Classifier: Programming Language :: Python :: 3
Classifier: License :: OSI Approved :: MIT License
Classifier: Operating System :: OS Independent
Requires-Python: >=3.9
License-File: LICENSE
Requires-Dist: requests
